queenbee_dsl/__init__.py
queenbee_dsl/cli.py
queenbee_dsl/common.py
queenbee_dsl/package.py
queenbee_dsl/alias/__init__.py
queenbee_dsl/alias/inputs.py
queenbee_dsl/alias/outputs.py
queenbee_dsl/dag/__init__.py
queenbee_dsl/dag/base.py
queenbee_dsl/dag/inputs.py
queenbee_dsl/dag/outputs.py
queenbee_dsl/dag/task.py
queenbee_dsl/function/__init__.py
queenbee_dsl/function/base.py
queenbee_dsl/function/inputs.py
queenbee_dsl/function/outputs.py
queenbee_dsl-0.7.2.dist-info/LICENSE
queenbee_dsl-0.7.2.dist-info/METADATA
queenbee_dsl-0.7.2.dist-info/WHEEL
queenbee_dsl-0.7.2.dist-info/entry_points.txt
queenbee_dsl-0.7.2.dist-info/top_level.txt
queenbee_dsl-0.7.2.dist-info/RECORD
