Metadata-Version: 2.1
Name: queenbee-dsl
Version: 0.7.2
Summary: A Python DSL for Queenbee workflow language.
Home-page: https://github.com/pollination/queenbee-python-dsl
Author: Pollination
Author-email: info@ladybug.tools
License: UNKNOWN
Platform: UNKNOWN
Classifier: Programming Language :: Python :: 3.7
Classifier: Programming Language :: Python :: Implementation :: CPython
Classifier: Operating System :: OS Independent
Requires-Python: >=3.7
Requires-Dist: queenbee (==1.22.16)
Requires-Dist: queenbee-local (==0.3.2)
Requires-Dist: click-plugins (==1.1.1)
Requires-Dist: importlib-metadata (==3.4.0)
Provides-Extra: pollination
Requires-Dist: queenbee-pollination (==0.7.4) ; extra == 'pollination'
Requires-Dist: click (==7.1.2) ; extra == 'pollination'
Requires-Dist: click-plugins (==1.1.1) ; extra == 'pollination'
